ausbills/__init__.py
ausbills/json_encoder.py
ausbills/log.py
ausbills/models.py
ausbills/parliament/__init__.py
ausbills/parliament/act.py
ausbills/parliament/federal.py
ausbills/parliament/nsw.py
ausbills/parliament/nt.py
ausbills/parliament/qld.py
ausbills/parliament/sa.py
ausbills/parliament/tas.py
ausbills/parliament/vic.py
ausbills/parliament/wa.py
ausbills/types.py
ausbills/util/__init__.py
ausbills/util/consts.py
ausbills-1.0.0.dist-info/LICENSE
ausbills-1.0.0.dist-info/WHEEL
ausbills-1.0.0.dist-info/METADATA
ausbills-1.0.0.dist-info/RECORD
