Metadata-Version: 2.1
Name: ausbills
Version: 1.0.0
Summary: Get current parliament bills from Australian governments.
License: MIT
Author: OpenGov Australia
Author-email: kip.crossing@gmail.com
Requires-Python: >=3.9,<4.0
Classifier: License :: OSI Approved :: MIT License
Classifier: Programming Language :: Python :: 3
Classifier: Programming Language :: Python :: 3.10
Classifier: Programming Language :: Python :: 3.9
Requires-Dist: PyMonad (>=2.4.0,<3.0.0)
Requires-Dist: bs4 (>=0.0.1,<0.0.2)
Requires-Dist: flake8 (>=3.9.2,<4.0.0)
Requires-Dist: lxml (>=4.6.3,<5.0.0)
Requires-Dist: pytest (>=6.2.4,<7.0.0)
Requires-Dist: requests (>=2.25.1,<3.0.0)
Requires-Dist: setuptools (>=57.0.0,<58.0.0)
Requires-Dist: urlpath (>=1.1.7,<2.0.0)
